LICENSE
MANIFEST.in
README.rst
setup.py
forms_extras/__init__.py
forms_extras/declarative.py
forms_extras/fields.py
forms_extras.egg-info/PKG-INFO
forms_extras.egg-info/SOURCES.txt
forms_extras.egg-info/dependency_links.txt
forms_extras.egg-info/top_level.txt
forms_extras/locale/ru/LC_MESSAGES/django.mo
forms_extras/locale/ru/LC_MESSAGES/django.po