Metadata-Version: 1.0
Name: forms-extras
Version: 0.1.1
Summary: Extra features, fields and widgets for Django forms
Home-page: https://github.com/freevoid/django-forms-extras
Author: Nikolay Zakharov
Author-email: nikolay@desh.su
License: MIT
Keywords: django forms widgets
Platform: UNKNOWN
Classifier: Development Status :: 3 - Alpha
Classifier: Intended Audience :: Developers
Classifier: Framework :: Django
Classifier: License :: OSI Approved :: MIT License
Classifier: Operating System :: OS Independent
Classifier: Programming Language :: Python
